res_sum/__init__.py
res_sum/research_summarizer.py
res_sum-0.1.1.dist-info/LICENSE
res_sum-0.1.1.dist-info/METADATA
res_sum-0.1.1.dist-info/WHEEL
res_sum-0.1.1.dist-info/dependency_links.txt
res_sum-0.1.1.dist-info/entry_points.txt
res_sum-0.1.1.dist-info/top_level.txt
res_sum-0.1.1.dist-info/RECORD
