Metadata-Version: 2.1
Name: res-sum
Version: 0.1.1
Summary: A Python package Leveraging LLMs for Research Synthesis
Home-page: https://github.com/drhammed/res-sum
Author: Hammed A. Akande
Author-email: "Hammed A. Akande" <akandehammedadedamola@gmail.com>
Project-URL: homepage, https://github.com/drhammed/res-sum
Project-URL: repository, https://github.com/drhammed/res-sum
Project-URL: issues, https://github.com/drhammed/res-sum/issues
Classifier: Development Status :: 3 - Alpha
Classifier: Intended Audience :: Developers
Classifier: Programming Language :: Python :: 3
Classifier: License :: OSI Approved :: MIT License
Classifier: Operating System :: OS Independent
Requires-Python: >=3.6
License-File: LICENSE
Requires-Dist: google-api-python-client
Requires-Dist: google-auth
Requires-Dist: google-auth-httplib2
Requires-Dist: google-auth-oauthlib
Requires-Dist: PyMuPDF
Requires-Dist: PyPDF2
Requires-Dist: python-docx
Requires-Dist: nltk
Requires-Dist: GDriveOps
Requires-Dist: voyageai
Requires-Dist: langchain
Requires-Dist: langchain-community
Requires-Dist: langchain-voyageai
Requires-Dist: langchain-groq
Requires-Dist: langchain-core
Requires-Dist: rouge-score
Requires-Dist: ipywidgets
Requires-Dist: scikit-learn
Provides-Extra: dev
Requires-Dist: pytest; extra == "dev"
Requires-Dist: pytest-cov; extra == "dev"
